sure/__init__.py
sure/_lazypredict.py
sure/distance_metrics.cpython-311-x86_64-linux-gnu.so
sure/utility.py
sure/distance_metrics/__init__.cpython-311-x86_64-linux-gnu.so
sure/distance_metrics/__init__.py
sure/distance_metrics/distance.cpython-311-x86_64-linux-gnu.so
sure/distance_metrics/distance.py
sure/distance_metrics/gower_matrix_c.pyx
sure/privacy/__init__.py
sure/privacy/privacy.cpython-311-x86_64-linux-gnu.so
sure/privacy/privacy.py
sure/report_generator/__init__.py
sure/report_generator/report_app.py
sure/report_generator/report_generator.cpython-311-x86_64-linux-gnu.so
sure/report_generator/report_generator.py
sure/report_generator/.streamlit/config.toml
sure/report_generator/pages/privacy.py
clearbox_sure-0.2.16.dist-info/METADATA
clearbox_sure-0.2.16.dist-info/WHEEL
clearbox_sure-0.2.16.dist-info/top_level.txt
clearbox_sure-0.2.16.dist-info/RECORD
clearbox_sure-0.2.16.dist-info/licenses/LICENSE
