Metadata-Version: 2.1
Name: clearbox-sure
Version: 0.2.16
Summary: A utility and privacy evaluation library for synthetic data
Home-page: https://github.com/Clearbox-AI/SURE
Author: Clearbox AI
Author-email: info@clearbox.ai
Requires-Python: >=3.7.0
License-File: LICENSE
Requires-Dist: clearbox-preprocessor
Requires-Dist: setuptools
Requires-Dist: pandas<=2.2.3
Requires-Dist: polars<=1.17.1
Requires-Dist: numpy<2.0.0
Requires-Dist: cython
Requires-Dist: wheel
Requires-Dist: streamlit
Requires-Dist: matplotlib
Requires-Dist: matplotlib-inline
Requires-Dist: seaborn
Requires-Dist: click
Requires-Dist: scikit-learn
Requires-Dist: tqdm
Requires-Dist: joblib
Requires-Dist: lightgbm
Requires-Dist: xgboost
Requires-Dist: sphinx-rtd-theme
Requires-Dist: myst-parser
